timewarpy/__init__.py
timewarpy/core.py
timewarpy/datasets.py
timewarpy/postprocess.py
timewarpy/preprocess.py
timewarpy/visuals.py
timewarpy/examples/__init__.py
timewarpy/examples/multivariate_rnn.py
timewarpy/examples/univariate_rnn.py
timewarpy/tests/__init__.py
timewarpy/tests/test_core.py
timewarpy/tests/test_datasets.py
timewarpy/tests/test_preprocess.py
timewarpy-0.0.22.dist-info/LICENSE
timewarpy-0.0.22.dist-info/METADATA
timewarpy-0.0.22.dist-info/WHEEL
timewarpy-0.0.22.dist-info/top_level.txt
timewarpy-0.0.22.dist-info/RECORD
