Metadata-Version: 2.1
Name: timewarpy
Version: 0.0.22
Summary: Time series processing framework and utilities for deep learning
Home-page: UNKNOWN
Author: Clay Elmore
License: BSD 3-Clause License
Platform: UNKNOWN
License-File: LICENSE
Requires-Dist: pandas (>=1.0.0)
